bnptool/__init__.py
bnptool/__main__.py
bnptool-1.0.2.dist-info/LICENSE
bnptool-1.0.2.dist-info/METADATA
bnptool-1.0.2.dist-info/WHEEL
bnptool-1.0.2.dist-info/entry_points.txt
bnptool-1.0.2.dist-info/top_level.txt
bnptool-1.0.2.dist-info/RECORD
