Metadata-Version: 2.1
Name: bnptool
Version: 1.0.2
Summary: A simple Commandline interface to create BNPs using BCML
Home-page: https://github.com/linktlh/bnptool
Author: linktlh
Author-email: linktlh@gmail.com
License: UNKNOWN
Platform: UNKNOWN
Classifier: Development Status :: 3 - Alpha
Classifier: License :: OSI Approved :: MIT License
Classifier: Operating System :: OS Independent
Classifier: Programming Language :: Python :: 3 :: Only
Requires-Python: >=3.7
License-File: LICENSE
Requires-Dist: bcml (>=3.0.0)
